README.txt
setup.py
django_fixture_generator.egg-info/PKG-INFO
django_fixture_generator.egg-info/SOURCES.txt
django_fixture_generator.egg-info/dependency_links.txt
django_fixture_generator.egg-info/top_level.txt
fixture_generator/__init__.py
fixture_generator/fixture_gen.py
fixture_generator/models.py
fixture_generator/management/__init__.py
fixture_generator/management/commands/__init__.py
fixture_generator/management/commands/generate_fixture.py
fixture_generator/tests/__init__.py
fixture_generator/tests/fixture_gen.py
fixture_generator/tests/models.py
fixture_generator/tests/tests.py