Metadata-Version: 1.0
Name: django-fixture-generator
Version: 0.2.0
Summary: django-fixture-generator is a reusable django application to make writing fixtures not suck.
Home-page: http://github.com/alex/django-fixture-generator/tree/master
Author: Alex Gaynor
Author-email: alex.gaynor@gmail.com
License: UNKNOWN
Platform: UNKNOWN
Classifier: Development Status :: 4 - Beta
Classifier: Environment :: Web Environment
Classifier: Intended Audience :: Developers
Classifier: License :: OSI Approved :: BSD License
Classifier: Operating System :: OS Independent
Classifier: Programming Language :: Python
Classifier: Framework :: Django
